aging/__init__.py
aging/__main__.py
aging/aging.py
aging/commands/__init__.py
aging/commands/guide_management.py
aging/commands/guide_navigation.py
aging/commands/main.py
aging/data/__init__.py
aging/data/config.py
aging/data/guides.py
aging/data/locations.py
aging/data/search_hits.py
aging/messages/__init__.py
aging/messages/clipboard.py
aging/messages/main.py
aging/providers/__init__.py
aging/providers/guides.py
aging/providers/main.py
aging/py.typed
aging/screens/__init__.py
aging/screens/about.py
aging/screens/main.py
aging/screens/search.py
aging/widgets/__init__.py
aging/widgets/entry_viewer/__init__.py
aging/widgets/entry_viewer/entry_content.py
aging/widgets/entry_viewer/see_also.py
aging/widgets/entry_viewer/widget.py
aging/widgets/guide_directory.py
aging/widgets/guide_menu.py
aging-1.2.0.dist-info/WHEEL
aging-1.2.0.dist-info/entry_points.txt
aging-1.2.0.dist-info/METADATA
aging-1.2.0.dist-info/RECORD
