Metadata-Version: 2.3
Name: aging
Version: 1.2.0
Summary: A Norton Guide reader for the terminal
Keywords: terminal,tui,chui,documentation,file-viewer,file-browser,norton-guide,help,ms-dos,clipper,xbase,dbase
Author: Dave Pearson
Author-email: Dave Pearson <davep@davep.org>
License: GNU General Public License v3 or later (GPLv3+)
Classifier: Development Status :: 5 - Production/Stable
Classifier: Environment :: Console
Classifier: Intended Audience :: Developers
Classifier: Intended Audience :: End Users/Desktop
Classifier: Intended Audience :: Information Technology
Classifier: Intended Audience :: Other Audience
Classifier: License :: OSI Approved :: GNU General Public License v3 or later (GPLv3+)
Classifier: Operating System :: MacOS
Classifier: Operating System :: Microsoft :: Windows :: Windows 10
Classifier: Operating System :: Microsoft :: Windows :: Windows 11
Classifier: Operating System :: POSIX :: Linux
Classifier: Programming Language :: Python :: 3 :: Only
Classifier: Programming Language :: Python :: 3
Classifier: Programming Language :: Python :: 3.10
Classifier: Programming Language :: Python :: 3.11
Classifier: Programming Language :: Python :: 3.12
Classifier: Programming Language :: Python :: 3.13
Classifier: Programming Language :: Python :: 3.14
Classifier: Topic :: Documentation
Classifier: Topic :: Software Development :: Documentation
Classifier: Topic :: Terminals
Classifier: Topic :: Utilities
Classifier: Typing :: Typed
Requires-Dist: textual>=3.4.0
Requires-Dist: textual-enhanced>=0.8.1
Requires-Dist: ngdb>=0.11.0
Requires-Dist: typing-extensions>=4.12.2
Requires-Dist: xdg-base-dirs>=6.0.2
Requires-Dist: textual-fspicker>=0.4.1
Requires-Dist: pyperclip>=1.9.0
Requires-Dist: humanize>=4.12.1
Requires-Python: >=3.10
Project-URL: Discussions, https://github.com/davep/aging/discussions
Project-URL: Documentation, https://github.com/davep/aging
Project-URL: Homepage, https://github.com/davep/aging
Project-URL: Issues, https://github.com/davep/aging/issues
Project-URL: Repository, https://github.com/davep/aging
Project-URL: Source, https://github.com/davep/aging
